{
  "date": "2026-07-10",
  "name": "Theme Park Rides",
  "theme": "Play",
  "special_day": "",
  "items": [
    { "id": "roller-coaster", "name": "Roller coaster", "emoji": "🎢" },
    { "id": "ferris-wheel", "name": "Ferris wheel", "emoji": "🎡" },
    { "id": "carousel", "name": "Carousel", "emoji": "🎠" },
    { "id": "bumper-cars", "name": "Bumper cars", "emoji": "🚗" },
    { "id": "log-flume", "name": "Log flume", "emoji": "🛶" },
    { "id": "drop-tower", "name": "Drop tower", "emoji": "🗼" },
    { "id": "ghost-train", "name": "Ghost train", "emoji": "👻" },
    { "id": "teacups", "name": "Teacups", "emoji": "🍵" },
    { "id": "pirate-ship", "name": "Pirate ship", "emoji": "🏴‍☠️" },
    { "id": "waltzer", "name": "Waltzer", "emoji": "🌀" },
    { "id": "dodgems", "name": "Dodgems", "emoji": "🚙" },
    { "id": "helter-skelter", "name": "Helter skelter", "emoji": "🛝" },
    { "id": "water-slide", "name": "Water slide", "emoji": "🏎️" },
    { "id": "go-karts", "name": "Go-karts", "emoji": "🎪" },
    { "id": "big-dipper", "name": "Big dipper", "emoji": "🏚️" },
    { "id": "haunted-house", "name": "Haunted house", "emoji": "🎛️" }
  ]
}
